ChanpinJingliShujufenxiShouceYuxiaosong/README.md
ChanpinJingliShujufenxiShouceYuxiaosong/__init__.py
ChanpinJingliShujufenxiShouceYuxiaosong/__main__.py
ChanpinJingliShujufenxiShouceYuxiaosong/file.pdf
ChanpinJingliShujufenxiShouceYuxiaosong/index.html
chanpin_jingli_shujufenxi_shouce_yuxiaosong-2024.3.4.0.dist-info/METADATA
chanpin_jingli_shujufenxi_shouce_yuxiaosong-2024.3.4.0.dist-info/WHEEL
chanpin_jingli_shujufenxi_shouce_yuxiaosong-2024.3.4.0.dist-info/entry_points.txt
chanpin_jingli_shujufenxi_shouce_yuxiaosong-2024.3.4.0.dist-info/top_level.txt
chanpin_jingli_shujufenxi_shouce_yuxiaosong-2024.3.4.0.dist-info/RECORD
